{
  "format_version": "1.10.0",
  "minecraft:client_entity": {
    "description": {
      "identifier": "minecraft:fireball",
      "materials": {
        "default": "fireball"
      },
      "textures": {
        "default": "textures/entity/projectiles/fireball"
      },
      "geometry": {
        "default": "geometry.fireball"
      },
      "animations": {
        "rotate": "animation.fireball.rotate"
      },
      "scripts": {
        "scale": "2.0",
        "animate": [
          "rotate"
        ]
      },
      "render_controllers": [ "controller.render.fireball" ]
    }
  }
}
